fast_csv_validator/__init__.py
fast_csv_validator/validator.py
fast_csv_validator/validator_2.py
fast_csv_validator-1.7.dist-info/AUTHORS
fast_csv_validator-1.7.dist-info/LICENSE
fast_csv_validator-1.7.dist-info/METADATA
fast_csv_validator-1.7.dist-info/WHEEL
fast_csv_validator-1.7.dist-info/entry_points.txt
fast_csv_validator-1.7.dist-info/top_level.txt
fast_csv_validator-1.7.dist-info/RECORD
