Metadata-Version: 2.1
Name: fast-csv-validator
Version: 1.7
Summary: A tool for validate csv file
Home-page: UNKNOWN
Author: von guan
Author-email: 
Maintainer: von guan
Maintainer-email: 
License: UNKNOWN
Platform: UNKNOWN
Classifier: Development Status :: 5 - Production/Stable
Classifier: Intended Audience :: Developers
Classifier: License :: OSI Approved :: MIT License
Classifier: Natural Language :: English
Classifier: Operating System :: OS Independent
Classifier: Programming Language :: Python :: 3
Classifier: Topic :: Software Development :: Libraries
Requires-Dist: xlsxwriter (>=1.3.0)
Requires-Dist: six (>=1.13)
